{
  "season": "2026",
  "hypercarDriverStandings": [
    {
      "position": 1,
      "wins": 1,
      "driver_name": "Sébastien Buemi Brendon Hartley Ryō Hirakawa",
      "team_name": "No. 8 Toyota Racing"
    },
    {
      "position": 2,
      "wins": 1,
      "driver_name": "René Rast Robin Frijns Sheldon van der Linde",
      "team_name": "No. 20 BMW M Team WRT"
    },
    {
      "position": 3,
      "wins": 1,
      "driver_name": "Mike Conway Kamui Kobayashi Nyck de Vries",
      "team_name": "No. 7 Toyota Racing"
    },
    {
      "position": 4,
      "wins": 1,
      "driver_name": "Kevin Magnussen Raffaele Marciello Dries Vanthoor",
      "team_name": "No. 15 BMW M Team WRT"
    }
  ],
  "hypercarTeamStandings": [
    {
      "position": 1,
      "wins": 1,
      "team_name": "No. 8 Toyota Racing"
    },
    {
      "position": 2,
      "wins": 1,
      "team_name": "No. 20 BMW M Team WRT"
    },
    {
      "position": 3,
      "wins": 1,
      "team_name": "No. 7 Toyota Racing"
    },
    {
      "position": 4,
      "wins": 1,
      "team_name": "No. 15 BMW M Team WRT"
    }
  ],
  "lmgt3DriverStandings": [
    {
      "position": 1,
      "wins": 1,
      "driver_name": "Dan Harper Anthony McIntosh Parker Thompson",
      "team_name": "No. 69 Team WRT"
    },
    {
      "position": 2,
      "wins": 1,
      "driver_name": "Antares Au Tom Fleming Marvin Kirchhöfer",
      "team_name": "No. 10 Garage 59"
    },
    {
      "position": 3,
      "wins": 1,
      "driver_name": "Nicky Catsburg Jonny Edgar Ben Keating",
      "team_name": "No. 33 TF Sport"
    },
    {
      "position": 4,
      "wins": 1,
      "driver_name": "Peter Dempsey Charlie Eastwood Salih Yoluç",
      "team_name": "No. 34 Racing Team Turkey by TF"
    }
  ],
  "lmgt3TeamStandings": [
    {
      "position": 1,
      "wins": 1,
      "team_name": "No. 69 Team WRT"
    },
    {
      "position": 2,
      "wins": 1,
      "team_name": "No. 10 Garage 59"
    },
    {
      "position": 3,
      "wins": 1,
      "team_name": "No. 33 TF Sport"
    },
    {
      "position": 4,
      "wins": 1,
      "team_name": "No. 34 Racing Team Turkey by TF"
    }
  ],
  "updated_at": "2026-07-13T10:31:12.145908+00:00"
}